random_insertion/__init__.py
random_insertion/_core.cp312-win_amd64.pyd
random_insertion/_core.pyi
random_insertion-0.3.0.post1.dist-info/licenses/LICENSE
random_insertion-0.3.0.post1.dist-info/METADATA
random_insertion-0.3.0.post1.dist-info/WHEEL
random_insertion-0.3.0.post1.dist-info/top_level.txt
random_insertion-0.3.0.post1.dist-info/RECORD
