Metadata-Version: 2.1
Name: random-insertion
Version: 0.3.0.post1
Summary: A library for performing fast random insertion on TSP and SHPP instances
Author: Furffico
License: Apache-2.0 license
Project-URL: Repository, https://github.com/Furffico/random-insertion
Project-URL: Issues, https://github.com/Furffico/random-insertion/issues
Classifier: License :: OSI Approved :: Apache Software License
Classifier: Intended Audience :: Science/Research
Classifier: Programming Language :: Python :: 3.7
Classifier: Programming Language :: C++
Classifier: Topic :: Scientific/Engineering :: Mathematics
Classifier: Topic :: Utilities
Requires-Python: >=3.7
License-File: LICENSE
Requires-Dist: numpy >=1.21
